{
  "name": "J치rn F칩tr",
  "description": "J치rn F칩tr\nTroll\nGod of War (2018)\n",
  "image": "https://static.wikia.nocookie.net/godofwar/images/f/f7/God_of_War_20180518181603.jpg/revision/latest/scale-to-width-down/268?cb=20180519040209",
  "biographicalInformation": {
    "birthplace": "The Mountain",
    "deathplace": "The Mountain",
    "location": "The Mountain",
    "status": "Deceased"
  },
  "physicalInformation": {
    "race": "Troll (Frost)",
    "gender": "Male",
    "skin_colour": "Ice blue"
  },
  "wiki": "https://godofwar.fandom.com/wiki/J%C3%A1rn_F%C3%B3tr"
}